difconnect/__init__.py
difconnect/__main__.py
difconnect/config.py
difconnect/dif.py
difconnect/scraper.py
difconnect-1.4.dist-info/LICENSE
difconnect-1.4.dist-info/METADATA
difconnect-1.4.dist-info/WHEEL
difconnect-1.4.dist-info/entry_points.txt
difconnect-1.4.dist-info/top_level.txt
difconnect-1.4.dist-info/RECORD
