Metadata-Version: 2.1
Name: difconnect
Version: 1.4
Summary: Parse WebSite for data and Connect to Diffusion Server
Home-page: https://github.com/zakharb/difconnect
Classifier: Programming Language :: Python :: 3
Classifier: License :: OSI Approved :: GNU General Public License v3 (GPLv3)
Classifier: Intended Audience :: Developers
Requires-Python: >=3.6
License-File: LICENSE
Requires-Dist: aiohttp (==3.8.4)
Requires-Dist: aiosignal (==1.3.1)
Requires-Dist: async-timeout (==4.0.2)
Requires-Dist: attrs (==20.3.0)
Requires-Dist: beautifulsoup4 (==4.12.0)
Requires-Dist: bs4 (==0.0.1)
Requires-Dist: cbor2 (==5.4.6)
Requires-Dist: certifi (==2022.12.7)
Requires-Dist: charset-normalizer (==3.1.0)
Requires-Dist: cloudscraper (==1.2.69)
Requires-Dist: diffusion (==6.8.7)
Requires-Dist: diffusion-core (==0.0.16)
Requires-Dist: frozenlist (==1.3.3)
Requires-Dist: idna (==3.4)
Requires-Dist: multidict (==6.0.4)
Requires-Dist: pydantic (==1.10.6)
Requires-Dist: pyparsing (==3.0.9)
Requires-Dist: requests (==2.28.2)
Requires-Dist: requests-toolbelt (==0.10.1)
Requires-Dist: soupsieve (==2.4)
Requires-Dist: stringcase (==1.2.0)
Requires-Dist: structlog (==20.2.0)
Requires-Dist: typing-extensions (==4.5.0)
Requires-Dist: urllib3 (==1.26.15)
Requires-Dist: yarl (==1.8.2)
